DESCRIPTION.rst
LICENSE.txt
MANIFEST.in
README.rst
setup.py
bash/iam_users.py
bash/keyup-completion.bash
keyup/__init__.py
keyup/_version.py
keyup/about.py
keyup/cauth.py
keyup/cli.py
keyup/colormap.py
keyup/colors.py
keyup/common.py
keyup/configuration.py
keyup/help_menu.py
keyup/iam_operations.py
keyup/keyconfig.py
keyup/list_ops.py
keyup/logd.py
keyup/map.py
keyup/menu.py
keyup/oscodes_unix.py
keyup/oscodes_win.py
keyup/progress_main.py
keyup/script_utils.py
keyup/statics.py
keyup/thread_progress.py
keyup/variables.py
keyup/vault.py
scripts/post-install.sh