Metadata-Version: 2.1
Name: keyup
Version: 1.3.1
Summary: Automated IAM Access Key Rotation for Amazon Web Services
Home-page: http://keyup.readthedocs.io
Author: Blake Huber
Author-email: blakeca00@gmail.com
License: GPL-3.0
Keywords: Amazon Web Services iam credentials AWS access key secret key
Classifier: Topic :: Security
Classifier: Development Status :: 5 - Production/Stable
Classifier: Programming Language :: Python :: 3.6
Classifier: Programming Language :: Python :: 3.7
Classifier: License :: OSI Approved :: GNU General Public License v3 (GPLv3)
Classifier: Operating System :: POSIX :: Linux
Classifier: Operating System :: Microsoft :: Windows
Requires-Python: >=3.6, <4
License-File: LICENSE.txt
